fontawesome47/__init__.py
fontawesome47/_version.py
fontawesome47/icons.py
fontawesome47/icons_bytes.py
fontawesome47/icons_str.py
fontawesome47/fonts/fontawesome-webfont.ttf
fontawesome47/fonts/icons.yml
fontawesome47-1.2.0.dist-info/METADATA
fontawesome47-1.2.0.dist-info/WHEEL
fontawesome47-1.2.0.dist-info/top_level.txt
fontawesome47-1.2.0.dist-info/RECORD
