Metadata-Version: 2.1
Name: fontawesome47
Version: 1.2.0
Summary: Font Awesome-4.7 for python desktop usage
Home-page: https://github.com/ousttrue/pyFontAwesome47/
Author: ousttrue
Author-email: ousttrue@gmail.com
License: UNKNOWN
Platform: UNKNOWN
Classifier: Programming Language :: Python :: 3
Classifier: License :: OSI Approved :: SIL Open Font License 1.1 (OFL-1.1)
Requires-Dist: pyyaml
